helga_weather
