Metadata-Version: 1.1
Name: helga-weather
Version: 1.0.1
Summary: Display weather from openweathermap.org
Home-page: https://github.com/narfman0/helga-weather
Author: Jon Robison
Author-email: narfman0@gmail.com
License: LICENSE
Keywords: irc bot weather urbandictionary urban dictionary ud
Platform: UNKNOWN
Classifier: Development Status :: 4 - Beta
Classifier: Topic :: Communications :: Chat :: Internet Relay Chat
Classifier: License :: OSI Approved :: GNU General Public License v3 (GPLv3)
Classifier: Operating System :: OS Independent
Classifier: Programming Language :: Python
Classifier: Topic :: Software Development :: Libraries :: Python Modules
Classifier: Topic :: Communications :: Chat :: Internet Relay Chat
